twogroups_heatmap/__init__.py
twogroups_heatmap/heatmap_code.py
twogroups_heatmap-0.1.3.dist-info/LICENSE
twogroups_heatmap-0.1.3.dist-info/METADATA
twogroups_heatmap-0.1.3.dist-info/WHEEL
twogroups_heatmap-0.1.3.dist-info/top_level.txt
twogroups_heatmap-0.1.3.dist-info/RECORD
