Metadata-Version: 2.1
Name: twogroups-heatmap
Version: 0.1.3
Summary: Create a heatmap of representing intersection between two groups
Home-page: https://github.com/HTGenomeAnalysisUnit/sc_2g_heatmap.git
Author: Giuditta Clerici
Author-email: Giuditta Clerici <giuditta.clerici@external.fht.org>, Edoardo Giacopuzzi <edoardo.giacopuzzi@external.fht.org>
License: Copyright (c) 2018 The Python Packaging Authority
Project-URL: Homepage, https://github.com/HTGenomeAnalysisUnit/sc_2g_heatmap.git
Project-URL: Issues, https://github.com/HTGenomeAnalysisUnit/sc_2g_heatmap/issues
Classifier: Programming Language :: Python :: 3
Classifier: License :: OSI Approved :: MIT License
Classifier: Operating System :: OS Independent
Requires-Python: >=3.6
License-File: LICENSE
Requires-Dist: seaborn >=0.12
Requires-Dist: pandas >=1.5
Requires-Dist: numpy >=1.23
Requires-Dist: matplotlib <3.7
